Metadata-Version: 2.2
Name: chrome_extension_python
Version: 1.0.3
Summary: Chrome Extension Python allows you to easily integrate Chrome extensions in web automation frameworks like Botasaurus, Selenium, and Playwright.
Home-page: https://github.com/omkarcloud/chrome-extension-python
Author: Chetan Jain
Author-email: chetan@omkar.cloud
License: MIT
Keywords: chrome-extension-python
Classifier: Development Status :: 5 - Production/Stable
Classifier: Topic :: Software Development :: Testing
Classifier: Topic :: System :: Installation/Setup
Classifier: Topic :: Software Development :: Libraries :: Python Modules
Classifier: License :: OSI Approved :: MIT License
Classifier: Programming Language :: Python :: 3
Classifier: Programming Language :: Python :: 3.6
Classifier: Programming Language :: Python :: 3.7
Classifier: Programming Language :: Python :: 3.8
Classifier: Programming Language :: Python :: 3.9
Classifier: Programming Language :: Python :: 3.10
Requires-Python: >=3.6
License-File: LICENSE
Dynamic: author
Dynamic: author-email
Dynamic: classifier
Dynamic: description
Dynamic: description-content-type
Dynamic: home-page
Dynamic: keywords
Dynamic: license
Dynamic: requires-python
Dynamic: summary
